odoo/addons/account_statement_import_file_reconcile_oca/README.rst
odoo/addons/account_statement_import_file_reconcile_oca/__init__.py
odoo/addons/account_statement_import_file_reconcile_oca/__manifest__.py
odoo/addons/account_statement_import_file_reconcile_oca/i18n/account_statement_import_file_reconcile_oca.pot
odoo/addons/account_statement_import_file_reconcile_oca/i18n/account_statement_import_file_reconciliation_widget.pot
odoo/addons/account_statement_import_file_reconcile_oca/i18n/es.po
odoo/addons/account_statement_import_file_reconcile_oca/i18n/fr.po
odoo/addons/account_statement_import_file_reconcile_oca/i18n/it.po
odoo/addons/account_statement_import_file_reconcile_oca/i18n/lv.po
odoo/addons/account_statement_import_file_reconcile_oca/readme/CONTRIBUTORS.md
odoo/addons/account_statement_import_file_reconcile_oca/readme/DESCRIPTION.md
odoo/addons/account_statement_import_file_reconcile_oca/readme/INSTALL.md
odoo/addons/account_statement_import_file_reconcile_oca/static/description/bank_statement_import_start_reconcile.png
odoo/addons/account_statement_import_file_reconcile_oca/static/description/icon.png
odoo/addons/account_statement_import_file_reconcile_oca/static/description/index.html
odoo/addons/account_statement_import_file_reconcile_oca/wizards/__init__.py
odoo/addons/account_statement_import_file_reconcile_oca/wizards/account_statement_import.py
odoo/addons/account_statement_import_file_reconcile_oca/wizards/account_statement_import_view.xml
odoo_addon_account_statement_import_file_reconcile_oca-18.0.1.0.0.3.dist-info/METADATA
odoo_addon_account_statement_import_file_reconcile_oca-18.0.1.0.0.3.dist-info/WHEEL
odoo_addon_account_statement_import_file_reconcile_oca-18.0.1.0.0.3.dist-info/top_level.txt
odoo_addon_account_statement_import_file_reconcile_oca-18.0.1.0.0.3.dist-info/RECORD
